{
  "connectors": [
    {
      "name": "testConn",
      "enabled": true,
      "url": "https://www.sina.com",
      "method": "GET",
      "queryParams": "1",
      "contentType": "2",
      "userAgent": "3",
      "type": "HTTP_CONNECTOR",
      "timeout": 3,
      "lang": "UTF-8"
    },
    {
      "name": "testConn2",
      "enabled": true,
      "url": "http://127.0.0.1:8080/test",
      "method": "POST",
      "queryParams": "2",
      "contentType": "application/json",
      "userAgent": "3",
      "timeout": 3000,
      "type": "HTTP_CONNECTOR",
      "lang": "UTF-8"
    }
  ]
}